README.md
setup.py
Shchirov_serializer.egg-info/PKG-INFO
Shchirov_serializer.egg-info/SOURCES.txt
Shchirov_serializer.egg-info/dependency_links.txt
Shchirov_serializer.egg-info/requires.txt
Shchirov_serializer.egg-info/top_level.txt
serializers/__init__.py
serializers/factory.py
serializers/base/__init__.py
serializers/base/constants.py
serializers/base/deserialization.py
serializers/base/serialization.py
serializers/json_serializer/JsonSerializer.py
serializers/json_serializer/__init__.py
serializers/json_serializer/serialization_logic.py
serializers/xml_serializer/XmlSerializer.py
serializers/xml_serializer/__init__.py
serializers/xml_serializer/serialization_logic.py
tests/tests.py