Metadata-Version: 2.1
Name: Shchirov-serializer
Version: 1.1.7
Summary: python library for serialization
Home-page: https://github.com/PaShampusik/PythonLabs/Lab_3
Author: PaShampusik
Author-email: shchirovpavel@gmail.com
Classifier: Programming Language :: Python :: 3.10
Classifier: Operating System :: OS Independent
